README.rst
setup.py
aioirc/__init__.py
aioirc/client.py
aioirc/connection.py
aioirc/event.py
aioirc/handler.py
aioirc.egg-info/PKG-INFO
aioirc.egg-info/SOURCES.txt
aioirc.egg-info/dependency_links.txt
aioirc.egg-info/top_level.txt