Metadata-Version: 1.1
Name: aioirc
Version: 0.1
Summary: AsyncIO IRC Library for >= Python 3.3
Home-page: https://github.com/devunt/aioirc
Author: JuneHyeon Bae
Author-email: devunt@gmail.com
License: License :: OSI Approved :: GNU Lesser General Public License v3 or later (LGPLv3+)
Keywords: irc,asyncio
Platform: UNKNOWN
Classifier: Development Status :: 2 - Pre-Alpha
Classifier: Intended Audience :: Developers
Classifier: License :: OSI Approved :: GNU Lesser General Public License v3 or later (LGPLv3+)
Classifier: Operating System :: OS Independent
Classifier: Programming Language :: Python
Classifier: Programming Language :: Python :: 3.3
Classifier: Programming Language :: Python :: 3.4
Classifier: Programming Language :: Python :: Implementation :: CPython
Classifier: Topic :: Software Development :: Libraries :: Application Frameworks
Classifier: Topic :: Software Development :: Libraries :: Python Modules
Classifier: Topic :: Communications :: Chat :: Internet Relay Chat
